eletter/__init__.py
eletter/classes.py
eletter/core.py
eletter/decompose.py
eletter/errors.py
eletter/py.typed
eletter/util.py
eletter-0.5.1.dist-info/METADATA
eletter-0.5.1.dist-info/WHEEL
eletter-0.5.1.dist-info/licenses/LICENSE
eletter-0.5.1.dist-info/RECORD
