Metadata-Version: 2.3
Name: eletter
Version: 0.5.1
Summary: Simple e-mail composition & decomposition
Project-URL: Source Code, https://github.com/jwodder/eletter
Project-URL: Bug Tracker, https://github.com/jwodder/eletter/issues
Project-URL: Documentation, https://eletter.readthedocs.io
Author-email: John Thorvald Wodder II <eletter@varonathe.org>
License: MIT
Keywords: EmailMessage,e-mail,email,message
Classifier: Intended Audience :: Developers
Classifier: Intended Audience :: Information Technology
Classifier: License :: OSI Approved :: MIT License
Classifier: Programming Language :: Python :: 3
Classifier: Programming Language :: Python :: 3 :: Only
Classifier: Programming Language :: Python :: 3.8
Classifier: Programming Language :: Python :: 3.9
Classifier: Programming Language :: Python :: 3.10
Classifier: Programming Language :: Python :: 3.11
Classifier: Programming Language :: Python :: 3.12
Classifier: Programming Language :: Python :: 3.13
Classifier: Programming Language :: Python :: Implementation :: CPython
Classifier: Programming Language :: Python :: Implementation :: PyPy
Classifier: Topic :: Communications :: Email
Classifier: Typing :: Typed
Requires-Python: >=3.8
Requires-Dist: attrs>=20.1
Requires-Dist: mailbits<1,>=0.2.1
